MANIFEST.in
README.md
requirements.txt
setup.cfg
setup.py
tripaille/__init__.py
tripaille/cli.py
tripaille/config.py
tripaille/decorators.py
tripaille/io.py
tripaille/commands/__init__.py
tripaille/commands/cmd_analysis.py
tripaille/commands/cmd_db.py
tripaille/commands/cmd_entity.py
tripaille/commands/cmd_expression.py
tripaille/commands/cmd_feature.py
tripaille/commands/cmd_init.py
tripaille/commands/cmd_job.py
tripaille/commands/cmd_organism.py
tripaille/commands/cmd_phylogeny.py
tripaille/commands/analysis/__init__.py
tripaille/commands/analysis/add_analysis.py
tripaille/commands/analysis/delete_orphans.py
tripaille/commands/analysis/get_analyses.py
tripaille/commands/analysis/get_analyses_tripal.py
tripaille/commands/analysis/load_blast.py
tripaille/commands/analysis/load_fasta.py
tripaille/commands/analysis/load_gff3.py
tripaille/commands/analysis/load_go.py
tripaille/commands/analysis/load_interpro.py
tripaille/commands/analysis/sync.py
tripaille/commands/db/__init__.py
tripaille/commands/db/get_dbs.py
tripaille/commands/db/get_mviews.py
tripaille/commands/db/index.py
tripaille/commands/db/populate_mviews.py
tripaille/commands/db/tune.py
tripaille/commands/entity/__init__.py
tripaille/commands/entity/add_entity.py
tripaille/commands/entity/get_bundles.py
tripaille/commands/entity/get_entities.py
tripaille/commands/entity/get_fields.py
tripaille/commands/entity/publish.py
tripaille/commands/expression/__init__.py
tripaille/commands/expression/add_biomaterial.py
tripaille/commands/expression/add_expression.py
tripaille/commands/expression/delete_biomaterials.py
tripaille/commands/expression/get_biomaterials.py
tripaille/commands/expression/get_biomaterials_tripal.py
tripaille/commands/expression/sync_biomaterials.py
tripaille/commands/feature/__init__.py
tripaille/commands/feature/delete_orphans.py
tripaille/commands/feature/get_features.py
tripaille/commands/feature/get_features_tripal.py
tripaille/commands/feature/sync.py
tripaille/commands/job/__init__.py
tripal.egg-info/PKG-INFO
tripal.egg-info/SOURCES.txt
tripal.egg-info/dependency_links.txt
tripal.egg-info/entry_points.txt
tripal.egg-info/requires.txt
tripal.egg-info/top_level.txt
