Metadata-Version: 1.1
Name: tripal
Version: 3.2.1
Summary: Tripal library
Home-page: https://github.com/galaxy-genome-annotation/python-tripal
Author: Anthony Bretaudeau
Author-email: anthony.bretaudeau@inra.fr
License: MIT
Platform: Posix; MacOS X; Windows
Classifier: Development Status :: 4 - Beta
Classifier: Intended Audience :: Developers
Classifier: License :: OSI Approved :: MIT License
Classifier: Operating System :: OS Independent
Classifier: Topic :: Scientific/Engineering
Classifier: Programming Language :: Python :: 2
Classifier: Programming Language :: Python :: 2.7
Classifier: Programming Language :: Python :: 3.4
Classifier: Programming Language :: Python :: 3.5
Classifier: Programming Language :: Python :: 3.6
